obsplanning.py
obsplanning-1.0.0.dist-info/LICENSE.txt
obsplanning-1.0.0.dist-info/METADATA
obsplanning-1.0.0.dist-info/WHEEL
obsplanning-1.0.0.dist-info/top_level.txt
obsplanning-1.0.0.dist-info/RECORD
