Metadata-Version: 2.1
Name: obsplanning
Version: 1.0.0
Summary: Various utilities to assist with astronomical observation planning
Home-page: https://github.com/pjcigan/obsplanning
Author: Phil Cigan
Author-email: pcigan@gmu.edu
License: MIT
Platform: UNKNOWN
License-File: LICENSE.txt
Requires-Dist: numpy
Requires-Dist: matplotlib
Requires-Dist: astropy
Requires-Dist: datetime
Requires-Dist: pytz
Requires-Dist: tzwhere
Requires-Dist: ephem
Requires-Dist: astroquery
Requires-Dist: scipy
Requires-Dist: tqdm
Requires-Dist: multicolorfits
